maipau/__init__.py
maipau/intro.py
Maipau-0.0.5.dist-info/LICENSE
Maipau-0.0.5.dist-info/METADATA
Maipau-0.0.5.dist-info/WHEEL
Maipau-0.0.5.dist-info/top_level.txt
Maipau-0.0.5.dist-info/RECORD
