Metadata-Version: 2.1
Name: Maipau
Version: 0.0.5
Summary: My first python package
Author: Maiipau
Classifier: Programming Language :: Python :: 3
Classifier: License :: OSI Approved :: MIT License
Classifier: Operating System :: OS Independent
Requires-Python: >=3.6
License-File: LICENSE
